helios/__init__.py
helios/__version__.py
helios/chunked_upload.py
helios/client.py
helios/exceptions.py
helios/requests.py
helios/responses.py
helios_client-0.5.20241122.post1.dist-info/METADATA
helios_client-0.5.20241122.post1.dist-info/WHEEL
helios_client-0.5.20241122.post1.dist-info/top_level.txt
helios_client-0.5.20241122.post1.dist-info/zip-safe
helios_client-0.5.20241122.post1.dist-info/RECORD
