Metadata-Version: 2.1
Name: helios-client
Version: 0.5.20241122.post1
Summary: Pure python 3 module to communicate with a Helios server.
Home-page: https://www.heliosmusic.io
Author: Cartesian Theatre
Author-email: kip@heliosmusic.io
License: LGPL
Project-URL: Bug Tracker, https://github.com/cartesiantheatre/python-helios-client/issues
Project-URL: Documentation, https://heliosmusic.io/api.html
Project-URL: Source Code, https://github.com/cartesiantheatre/python-helios-client
Keywords: music,similarity,match,catalogue,digital,signal,processing,machine,learning
Classifier: Development Status :: 4 - Beta
Classifier: Environment :: Console
Classifier: Intended Audience :: Developers
Classifier: License :: OSI Approved :: GNU Lesser General Public License v3 or later (LGPLv3+)
Classifier: Operating System :: OS Independent
Classifier: Programming Language :: Python
Classifier: Programming Language :: Python :: 3 :: Only
Classifier: Programming Language :: ML
Classifier: Topic :: Database :: Database Engines/Servers
Classifier: Topic :: Internet
Classifier: Topic :: Internet :: WWW/HTTP
Classifier: Topic :: Internet :: WWW/HTTP :: Indexing/Search
Classifier: Topic :: Multimedia :: Sound/Audio
Classifier: Topic :: Multimedia :: Sound/Audio :: Analysis
Classifier: Topic :: Scientific/Engineering :: Artificial Intelligence
Classifier: Topic :: Scientific/Engineering :: Physics
Classifier: Topic :: Software Development :: Libraries :: Python Modules
Requires-Python: >= 3.7
Requires-Dist: attrs >=18.2.0
Requires-Dist: brotli
Requires-Dist: marshmallow >=3.16.0
Requires-Dist: requests
Requires-Dist: requests-toolbelt
Requires-Dist: simplejson
Requires-Dist: tqdm
Requires-Dist: urllib3
